conannio/__init__.py
conannio-0.4.0.dist-info/LICENSE
conannio-0.4.0.dist-info/METADATA
conannio-0.4.0.dist-info/WHEEL
conannio-0.4.0.dist-info/top_level.txt
conannio-0.4.0.dist-info/RECORD
