Metadata-Version: 2.1
Name: conannio
Version: 0.4.0
Summary: Conan Extension
Home-page: https://github.com/swysocki/gpt-image
Author: Scott Wysocki
Author-email: zzgmtv@163.com
License: MIT
License-File: LICENSE
Requires-Dist: conan (==1.58.0)
